{
  "name": "Armor of Radiant Resistance, Hide",
  "type": "equipment",
  "system": {
    "description": {
      "value": "<p>You have resistance to radiant damage while you wear this armor.</p>",
      "chat": "",
      "unidentified": null
    },
    "source": "Basic Rules, Player's Handbook",
    "quantity": 1,
    "weight": 12,
    "price": 0,
    "attunement": 1,
    "equipped": false,
    "rarity": "rare",
    "identified": true,
    "activation": {
      "type": "",
      "cost": null,
      "condition": ""
    },
    "duration": {
      "value": null,
      "units": ""
    },
    "cover": null,
    "crewed": false,
    "target": {
      "value": null,
      "width": null,
      "units": "",
      "type": ""
    },
    "range": {
      "value": null,
      "long": null,
      "units": ""
    },
    "uses": {
      "value": null,
      "max": 0,
      "per": null,
      "recovery": ""
    },
    "consume": {
      "type": "",
      "target": null,
      "amount": null
    },
    "ability": null,
    "actionType": "",
    "attackBonus": 0,
    "chatFlavor": "",
    "critical": {
      "threshold": null,
      "damage": ""
    },
    "damage": {
      "parts": [],
      "versatile": ""
    },
    "formula": "",
    "save": {
      "ability": "",
      "dc": null,
      "scaling": "spell"
    },
    "armor": {
      "value": 12,
      "type": "medium",
      "dex": 2
    },
    "hp": {
      "value": 0,
      "max": 0,
      "dt": null,
      "conditions": ""
    },
    "baseItem": "hide",
    "speed": {
      "value": null,
      "conditions": ""
    },
    "strength": null,
    "stealth": false,
    "proficient": true,
    "toolType": "",
    "properties": {
      "mgc": true
    }
  },
  "flags": {
    "ddbimporter": {
      "dndbeyond": {
        "type": null,
        "avatarUrl": "https://www.dndbeyond.com/avatars/9334/773/637206653909636510.jpeg",
        "largeAvatarUrl": "https://www.dndbeyond.com/avatars/9334/774/637206653911032971.jpeg",
        "filterType": "Armor",
        "isConsumable": false,
        "isContainer": false,
        "isCustomItem": false,
        "isHomebrew": false,
        "isMonkWeapon": false,
        "isPack": false,
        "levelInfusionGranted": null,
        "tags": [
          "Combat",
          "Warding"
        ],
        "sources": [
          {
            "sourceId": 1,
            "pageNumber": null,
            "sourceType": 2
          },
          {
            "sourceId": 2,
            "pageNumber": null,
            "sourceType": 1
          }
        ],
        "pictureUrl": "https://www.dndbeyond.com/avatars/9334/774/637206653911032971.jpeg"
      },
      "id": 0,
      "entityTypeId": 0,
      "definitionEntityTypeId": 112130694,
      "definitionId": 5064,
      "originalName": "Armor of Radiant Resistance, Hide",
      "version": "3.1.17",
      "effectsApplied": true
    },
    "magicitems": {
      "enabled": true,
      "charges": "0",
      "chargeType": "c1",
      "rechargeable": false,
      "recharge": "0",
      "rechargeType": "t2",
      "rechargeUnit": "r1",
      "destroy": false,
      "destroyCheck": "d1",
      "spells": {},
      "feats": {},
      "tables": {},
      "equipped": true,
      "attuned": false,
      "destroyFlavorText": "reaches 0 charges: it crumbles into ashes and is destroyed.",
      "sorting": "l"
    },
    "dae": {
      "alwaysActive": false,
      "activeEquipped": true
    },
    "cf": {
      "id": "temp_t3gve6b86a8"
    }
  },
  "effects": [
    {
      "label": "Armor of Radiant Resistance, Hide - Constant Effects",
      "icon": "icons/equipment/chest/breastplate-banded-simple-leather-brown.webp",
      "changes": [
        {
          "key": "system.traits.dr.value",
          "value": "radiant",
          "mode": 0,
          "priority": 1
        }
      ],
      "duration": {
        "startTime": null,
        "seconds": null,
        "combat": null,
        "rounds": null,
        "turns": null,
        "startRound": null,
        "startTurn": null
      },
      "tint": null,
      "transfer": true,
      "disabled": false,
      "flags": {
        "dae": {
          "transfer": true,
          "stackable": "none"
        },
        "ddbimporter": {
          "disabled": false,
          "itemId": 0,
          "itemEntityTypeId": 0
        },
        "midi-qol": {
          "forceCEOff": true
        }
      },
      "_id": "CRBuHHq10eDuQ4Pw",
      "origin": null,
      "_key": "!items.effects!s4KxHwWzsgFaPjbN.CRBuHHq10eDuQ4Pw"
    }
  ],
  "img": "icons/equipment/chest/breastplate-banded-simple-leather-brown.webp",
  "_stats": {
    "systemId": "dnd5e",
    "systemVersion": "2.3.0",
    "coreVersion": "11.307",
    "createdTime": 1666010239933,
    "modifiedTime": 1692222821602,
    "lastModifiedBy": "packsbuilder0000"
  },
  "ownership": {
    "default": 0
  },
  "folder": "8lByl5QXVoSmAWz2",
  "sort": 0,
  "_id": "s4KxHwWzsgFaPjbN",
  "_key": "!items!s4KxHwWzsgFaPjbN"
}
